shift_print
