Metadata-Version: 1.0
Name: shift-print
Version: 0.1.1
Summary: Tools for shifting scope's output
Home-page: https://bitbucket.org/Nikita_Vlaznev/shift-print
Author: Nikita Vlaznev
Author-email: nikita.dto@gmail.com
License: MIT
Keywords: print offset shift tabulation stdout
Platform: UNKNOWN
